{
  "stocks": [
    {
      "symbol": "RELIANCE.NS",
      "name": "Reliance Industries Limited",
      "price": 1486.9,
      "previousClose": 1484.1,
      "change": 2.8,
      "changePercent": 0.19,
      "dayHigh": 1492.0,
      "dayLow": 1477.6,
      "open": 1484.1,
      "fiftyTwoWeekHigh": 1551.0,
      "fiftyTwoWeekLow": 1114.85,
      "marketCap": 20121433145344,
      "pe": 24.2,
      "eps": 61.44,
      "volume": 17628910,
      "averageVolume": 10478225,
      "sector": "Energy",
      "industry": "Oil & Gas Refining & Marketing",
      "dividendYield": 37.0,
      "bookValue": 648.12,
      "priceToBook": 2.29,
      "lastUpdate": "2025-10-29 00:29:59",
      "currency": "INR"
    },
    {
      "symbol": "TCS.NS",
      "name": "Tata Consultancy Services Limited",
      "price": 3057.9,
      "previousClose": 3084.9,
      "change": -27.0,
      "changePercent": -0.88,
      "dayHigh": 3090.2,
      "dayLow": 3040.2,
      "open": 3076.0,
      "fiftyTwoWeekHigh": 4494.9,
      "fiftyTwoWeekLow": 2866.6,
      "marketCap": 11063748722688,
      "pe": 22.38,
      "eps": 136.66,
      "volume": 3470492,
      "averageVolume": 2950602,
      "sector": "Technology",
      "industry": "Information Technology Services",
      "dividendYield": 201.0,
      "bookValue": 294.12,
      "priceToBook": 10.4,
      "lastUpdate": "2025-10-29 00:29:59",
      "currency": "INR"
    },
    {
      "symbol": "INFY.NS",
      "name": "Infosys Limited",
      "price": 1500.2,
      "previousClose": 1504.5,
      "change": -4.3,
      "changePercent": -0.29,
      "dayHigh": 1506.5,
      "dayLow": 1490.5,
      "open": 1499.7,
      "fiftyTwoWeekHigh": 2006.45,
      "fiftyTwoWeekLow": 1307.0,
      "marketCap": 6218793877504,
      "pe": 21.63,
      "eps": 69.36,
      "volume": 8196804,
      "averageVolume": 8165295,
      "sector": "Technology",
      "industry": "Information Technology Services",
      "dividendYield": 299.0,
      "bookValue": 2.81,
      "priceToBook": 534.45,
      "lastUpdate": "2025-10-29 00:30:00",
      "currency": "INR"
    }
  ],
  "indices": {
    "nifty50": {
      "symbol": "^NSEI",
      "name": "NIFTY 50",
      "type": "index",
      "price": 25936.2,
      "previousClose": 25966.05,
      "change": -29.85,
      "changePercent": -0.11,
      "dayHigh": 26041.7,
      "dayLow": 25810.05,
      "open": 25939.95,
      "fiftyTwoWeekHigh": 26104.2,
      "fiftyTwoWeekLow": 21743.65,
      "lastUpdate": "2025-10-29 00:30:00"
    },
    "sensex": {
      "symbol": "^BSESN",
      "name": "SENSEX",
      "type": "index",
      "price": 84628.16,
      "previousClose": 84778.84,
      "change": -150.68,
      "changePercent": -0.18,
      "dayHigh": 84986.94,
      "dayLow": 84219.39,
      "open": 84625.71,
      "fiftyTwoWeekHigh": 85290.06,
      "fiftyTwoWeekLow": 71425.01,
      "lastUpdate": "2025-10-29 00:30:02"
    }
  },
  "last_update": "2025-10-29 00:30:02"
}